xyz_aws/__init__.py
xyz_aws/s3.py
xyz_aws/utils.py
xyz_aws-0.1.6.dist-info/METADATA
xyz_aws-0.1.6.dist-info/WHEEL
xyz_aws-0.1.6.dist-info/top_level.txt
xyz_aws-0.1.6.dist-info/RECORD
